ibis/__init__.py
ibis/compiler.py
ibis/context.py
ibis/errors.py
ibis/filters.py
ibis/loaders.py
ibis/nodes.py
ibis/template.py
ibis/utils.py
ibis-3.3.0.dist-info/METADATA
ibis-3.3.0.dist-info/WHEEL
ibis-3.3.0.dist-info/top_level.txt
ibis-3.3.0.dist-info/RECORD
